setup.py
entigen/__init__.py
entigen/block.py
entigen/errors.py
entigen/extensible.py
entigen/main.py
entigen/model.py
entigen/types.py
entigen/utils.py
entigen.egg-info/PKG-INFO
entigen.egg-info/SOURCES.txt
entigen.egg-info/dependency_links.txt
entigen.egg-info/entry_points.txt
entigen.egg-info/requires.txt
entigen.egg-info/top_level.txt
entigen/readers/__init__.py
entigen/readers/csv.py
entigen/writers/__init__.py
entigen/writers/info.py
entigen/writers/python.py
entigen/writers/sqlalchemy.py