Metadata-Version: 1.1
Name: entigen
Version: 0.1.2
Summary: Metamodel entity generator
Home-page: UNKNOWN
Author: Stefan Urbanek
Author-email: stefan.urbanek@gmail.com
License: MIT
Platform: UNKNOWN
Classifier: Development Status :: 3 - Alpha
Classifier: Intended Audience :: Developers
Classifier: License :: OSI Approved :: MIT License
Classifier: Programming Language :: Python :: 3
Classifier: Programming Language :: Python :: 3.5
